{
 "actions": [],
 "autoname": "hash",
 "creation": "2022-10-19 12:17:46.079493",
 "doctype": "DocType",
 "editable_grid": 1,
 "engine": "InnoDB",
 "field_order": [
  "employee",
  "employee_name",
  "basic_salary",
  "loan_amount"
 ],
 "fields": [
  {
   "fieldname": "employee",
   "fieldtype": "Link",
   "in_list_view": 1,
   "label": "Employee",
   "options": "Employee",
   "reqd": 1
  },
  {
   "fieldname": "employee_name",
   "fieldtype": "Data",
   "label": "Employee Name",
   "read_only": 1
  },
  {
   "fieldname": "basic_salary",
   "fieldtype": "Currency",
   "label": "Basic Salary",
   "options": "currency",
   "read_only": 1
  },
  {
   "fieldname": "loan_amount",
   "fieldtype": "Currency",
   "label": "Loan Amount",
   "options": "currency"
  }
 ],
 "index_web_pages_for_search": 1,
 "istable": 1,
 "links": [],
 "modified": "2022-10-28 10:53:00.997161",
 "modified_by": "Administrator",
 "module": "Paie Congo",
 "name": "Loan Employee details",
 "naming_rule": "Random",
 "owner": "Administrator",
 "permissions": [],
 "sort_field": "modified",
 "sort_order": "DESC",
 "states": []
}